custom_pkg_dmo/__init__.py
custom_pkg_dmo/package1/__init__.py
custom_pkg_dmo/package1/arithmetic.py
custom_pkg_dmo/package2/__init__.py
custom_pkg_dmo/package2/bitcompare.py
custom_pkg_dmo/package2/comparison.py
custom_pkg_dmo-0.0.1.dist-info/LICENCE.txt
custom_pkg_dmo-0.0.1.dist-info/METADATA
custom_pkg_dmo-0.0.1.dist-info/WHEEL
custom_pkg_dmo-0.0.1.dist-info/top_level.txt
custom_pkg_dmo-0.0.1.dist-info/RECORD
