Metadata-Version: 2.1
Name: custom-pkg-dmo
Version: 0.0.1
Summary: A very basic package
Author: Imran Nazir
Author-email: imrnazir8@gmail.com
Classifier: Programming Language :: Python :: 3
Classifier: License :: OSI Approved :: MIT License
Classifier: Operating System :: OS Independent
License-File: LICENCE.txt
